{
    "project": "Praesec Infrastructure",
    "domain": "praesecinfra.com",
  
    "trust_model": "dns-anchored transparency log",
    "hash_algorithm": "sha256",
    "signature_algorithm": "ed25519",
  
    "latest_epoch": 4,
    "latest_tree_size": 2,
  
    "bundles": [
      {
        "epoch": 3,
        "type": "merkle+inclusion",
        "file": "/bundles/praesec-merkle-bundle-v1.zip",
        "root": "7e49c6a51fd597112c7df013624db82ed0f4f593268cc72eb3f36d7537d431da",
        "verified": true
      },
      {
        "epoch": 4,
        "type": "transparency+consistency",
        "file": "/bundles/praesec-transparency-bundle-v1.zip",
        "root": "a90d74af9b619bdf084ef9bed23ba737ee671d065eb5ffe22ce58b386e981320",
        "signed_at": "2026-02-09T21:00:00Z",
        "verified": true
      }
    ],
  
    "discovery": {
      "manifest": "/.well-known/praesec.json",
      "merkle_root_dns": "_praesec-merkle.praesecinfra.com",
      "consistency_dns": "_praesec-consistency.praesecinfra.com"
    },
  
    "security_model": {
      "append_only": true,
      "multi_witness_consensus": true,
      "cryptographic_root_signing": true,
      "cryptographic_state_signing": true,
      "offline_verifiability": true
    },
  
    "signed_state_hash": "d4420129dbf14facdf3245eb92387b2a7b5cd3d6db4f855cd545c279cc032b22",
  
    "state_signature": "ZvUh3O5uh8Fg//C0iFrzP0MDlG2P0xyjSJu2yJ+SJKxiAvHlKdYxazPS4vq9nKmej6JvsAxzx8j1D4SRTMO3Ag==",
  
    "state_public_key": "MCowBQYDK2VwAyEAujk7q5+dnPYuyT8GqBkblwfq4KuFLdwftwhIVzOZTqg=",
  
    "signed_at": "2026-02-16T06:40:00Z",
  
    "last_updated": "2026-02-16"
  }